README.md
setup.cfg
setup.py
simpleplotlib/__init__.py
simpleplotlib.egg-info/PKG-INFO
simpleplotlib.egg-info/SOURCES.txt
simpleplotlib.egg-info/dependency_links.txt
simpleplotlib.egg-info/requires.txt
simpleplotlib.egg-info/top_level.txt