Metadata-Version: 1.1
Name: simpleplotlib
Version: 0.17
Summary: A matplotlib wrapper focused on beauty and simplicity
Home-page: https://github.com/mukerjee/simpleplotlib
Author: Matthew K. Mukerjee
Author-email: Matthew.Mukerjee@gmail.com
License: MIT License
Download-URL: https://github.com/mukerjee/simpleplotlib/tarball/0.17
Keywords: matplotlib,plots,beauty,simplicity
Platform: UNKNOWN
Classifier: Development Status :: 3 - Alpha
Classifier: Intended Audience :: Science/Research
Classifier: License :: OSI Approved :: MIT License
Classifier: Operating System :: OS Independent
Classifier: Programming Language :: Python :: 2.6
Classifier: Programming Language :: Python :: 2.7
Classifier: Programming Language :: Python :: 3.3
Classifier: Topic :: Scientific/Engineering
